odoo8_addon_purchase_delivery_split_date-8.0.1.0.0.99.dev9-py3.8-nspkg.pth
odoo_addons/purchase_delivery_split_date/README.rst
odoo_addons/purchase_delivery_split_date/__init__.py
odoo_addons/purchase_delivery_split_date/__openerp__.py
odoo_addons/purchase_delivery_split_date/purchase.py
odoo_addons/purchase_delivery_split_date/i18n/de.po
odoo_addons/purchase_delivery_split_date/i18n/es.po
odoo_addons/purchase_delivery_split_date/i18n/fi.po
odoo_addons/purchase_delivery_split_date/i18n/fr.po
odoo_addons/purchase_delivery_split_date/i18n/fr_FR.po
odoo_addons/purchase_delivery_split_date/i18n/it.po
odoo_addons/purchase_delivery_split_date/i18n/nl.po
odoo_addons/purchase_delivery_split_date/i18n/pt_BR.po
odoo_addons/purchase_delivery_split_date/i18n/purchase_delivery_split_date.pot
odoo_addons/purchase_delivery_split_date/i18n/ro.po
odoo_addons/purchase_delivery_split_date/i18n/sl.po
odoo_addons/purchase_delivery_split_date/static/description/icon.png
odoo_addons/purchase_delivery_split_date/tests/__init__.py
odoo_addons/purchase_delivery_split_date/tests/test_purchase_delivery.py
odoo8_addon_purchase_delivery_split_date-8.0.1.0.0.99.dev9.dist-info/METADATA
odoo8_addon_purchase_delivery_split_date-8.0.1.0.0.99.dev9.dist-info/WHEEL
odoo8_addon_purchase_delivery_split_date-8.0.1.0.0.99.dev9.dist-info/namespace_packages.txt
odoo8_addon_purchase_delivery_split_date-8.0.1.0.0.99.dev9.dist-info/top_level.txt
odoo8_addon_purchase_delivery_split_date-8.0.1.0.0.99.dev9.dist-info/RECORD
